deepcoil/__init__.py
deepcoil/deepcoil.py
deepcoil/models/seq.json
deepcoil/run_deepcoil.py
deepcoil/utils/__init__.py
deepcoil/utils/encoders.py
deepcoil/utils/generators.py
deepcoil/utils/seqvec.py
deepcoil/utils/utils.py
deepcoil/weights/seq_1.h5
deepcoil/weights/seq_2.h5
deepcoil/weights/seq_3.h5
deepcoil/weights/seq_4.h5
deepcoil/weights/seq_5.h5
deepcoil-2.0.2.dist-info/entry_points.txt
deepcoil-2.0.2.dist-info/WHEEL
deepcoil-2.0.2.dist-info/METADATA
deepcoil-2.0.2.dist-info/RECORD
