Metadata-Version: 2.1
Name: deepcoil
Version: 2.0.2
Summary: Fast and accurate prediction of coiled coil domains in protein sequences
Author: Jan Ludwiczak
Author-email: j.ludwiczak@cent.uw.edu.pl
Requires-Python: <3.9
Classifier: Programming Language :: Python :: 2
Classifier: Programming Language :: Python :: 2.7
Classifier: Programming Language :: Python :: 3
Classifier: Programming Language :: Python :: 3.4
Classifier: Programming Language :: Python :: 3.5
Classifier: Programming Language :: Python :: 3.6
Classifier: Programming Language :: Python :: 3.7
Classifier: Programming Language :: Python :: 3.8
Requires-Dist: allennlp (==0.9.0)
Requires-Dist: biopython (==1.79)
Requires-Dist: overrides (==3.1.0)
Requires-Dist: pandas (==1.3.0)
Requires-Dist: seaborn (>=0.12.0,<0.13.0)
Requires-Dist: tensorflow (>=2.3,<3.0)
